README.rst
setup.py
djnotification/__init__.py
djnotification/admin.py
djnotification/apps.py
djnotification/consumers.py
djnotification/serializers.py
djnotification/tasks.py
djnotification/tests.py
djnotification/urls.py
djnotification/views.py
djnotification.egg-info/PKG-INFO
djnotification.egg-info/SOURCES.txt
djnotification.egg-info/dependency_links.txt
djnotification.egg-info/requires.txt
djnotification.egg-info/top_level.txt
djnotification/migrations/0001_initial.py
djnotification/migrations/__init__.py
djnotification/models/__init__.py
djnotification/models/group.py
djnotification/models/notification.py
djnotification/models/subscription.py
djnotification/models/user.py