Metadata-Version: 2.1
Name: djnotification
Version: 0.1
Summary: Django Notification App
Home-page: https://github.com/shirani98/djnotification
Author: Mahdi Shirani
Author-email: Shirani9882@gmail.com
License: MIT
Platform: UNKNOWN
Classifier: Development Status :: 3 - Alpha
Classifier: Framework :: Django
Classifier: Intended Audience :: Developers
Classifier: License :: OSI Approved :: MIT License
Classifier: Programming Language :: Python :: 3
Classifier: Programming Language :: Python :: 3.9
Classifier: Programming Language :: Python :: 3.10
Classifier: Programming Language :: Python :: 3.11
